<root>
	<Entity type="Trigger" subType="start_level04_mission_03" >
		<!--<GraphicsComponent>
			<Model modelPath="Data/Resource/Model/Prop/SM_dev_box.fbx" shaderPath="Data/Resource/Shader/S_effect_pbl_deferred.fx" />
			<RoomType value="static"/>
		</GraphicsComponent>-->
		
		<TriggerComponent>
			<Trigger type="startMission" value="3" oneTimeTrigger="false" isClientSide="false"  activeFromStart="false" isPressable="false"/>
		</TriggerComponent>
		
		<PhysicsComponent>
			<min x="0" y="0" z="0"/>
			<max x="7.5" y="3.069767" z="7.5"/>
			<type value="trigger"/>
		</PhysicsComponent>
	</Entity>
</root>